renview/Installation_Steps.pdf
renview/__init__.py
renview/run.py
renview/GraphGenerator/__init__.py
renview/Pathways/__init__.py
renview/data/example_ammonia/pathways_ammonia.txt
renview/data/example_ammonia/reaction_rates.out
renview/data/example_ammonia/species_comp.out
renview/data/example_ammonia/Images/renview.png
renview/data/example_gu_long_contact_time/reaction_rates.out
renview/data/example_gu_long_contact_time/species_comp.out
renview/data/example_gu_short_contact_time/reaction_rates.out
renview/data/example_gu_short_contact_time/species_comp.out
renview/data/example_sutton/reaction_rates.out
renview/data/example_sutton/species_comp.out
renview/img/ReactionInput.png
renview/img/SpeciesInput.png
renview/img/renview.png
renview-1.6.0.dist-info/LICENSE.md
renview-1.6.0.dist-info/METADATA
renview-1.6.0.dist-info/WHEEL
renview-1.6.0.dist-info/top_level.txt
renview-1.6.0.dist-info/RECORD
